apollo/__init__.py
apollo/apollo_client.py
apollo/util.py
tests/__init__.py
tests/apollo_client_test.py
CoApollo-0.0.2.dist-info/LICENSE.txt
CoApollo-0.0.2.dist-info/METADATA
CoApollo-0.0.2.dist-info/WHEEL
CoApollo-0.0.2.dist-info/top_level.txt
CoApollo-0.0.2.dist-info/RECORD
